odoo/addons/web_no_bubble/README.rst
odoo/addons/web_no_bubble/__init__.py
odoo/addons/web_no_bubble/__manifest__.py
odoo/addons/web_no_bubble/static/description/icon.png
odoo/addons/web_no_bubble/static/src/css/web_no_bubble.css
odoo/addons/web_no_bubble/views/web_no_bubble.xml
odoo11_addon_web_no_bubble-11.0.1.0.0.dist-info/DESCRIPTION.rst
odoo11_addon_web_no_bubble-11.0.1.0.0.dist-info/METADATA
odoo11_addon_web_no_bubble-11.0.1.0.0.dist-info/RECORD
odoo11_addon_web_no_bubble-11.0.1.0.0.dist-info/WHEEL
odoo11_addon_web_no_bubble-11.0.1.0.0.dist-info/metadata.json
odoo11_addon_web_no_bubble-11.0.1.0.0.dist-info/top_level.txt
